{
	"parent": "block/block",
	"textures": {
		"particle": "chinjufumod:blocks/kitchen_front",
		"top": "chinjufumod:blocks/kitchen_top",
		"front": "chinjufumod:blocks/kitchen_front",
		"side": "chinjufumod:blocks/kitchen_side",
		"hiki": "chinjufumod:blocks/muku_bir",
		"bon": "chinjufumod:blocks/muku_spru",
		"tea": "chinjufumod:blocks/tea_red",
		"cup": "chinjufumod:blocks/dish_white",
		"cup2": "chinjufumod:blocks/dish_pink",
		"sara": "chinjufumod:blocks/dish_white",
		"pot": "chinjufumod:blocks/dish_white",
		"pot2": "chinjufumod:blocks/dish_lightb"
	},
    "elements": [

    	{
			"name": "teasara_soko_n__________________________bbbbbbbbbbbbbbb",
			"from": [ 11.5, 5, 5.0 ],
			"to": [ 13.5, 5.2, 5.2 ],
			"faces": {
				"down" : { "texture": "#sara" },
				"north": { "texture": "#sara" },
				"south": { "texture": "#sara" },
				"west" : { "texture": "#sara" },
				"east" : { "texture": "#sara" }
			}
		},
		{
			"name": "teasara_soko_s",
			"from": [ 11.5, 5, 6.8 ],
			"to": [ 13.5, 5.2, 7.0 ],
			"faces": {
				"down" : { "texture": "#sara" },
				"north": { "texture": "#sara" },
				"south": { "texture": "#sara" },
				"west" : { "texture": "#sara" },
				"east" : { "texture": "#sara" }
			}
		},
		{
			"name": "teasara_soko_w",
			"from": [ 11.5, 5, 5.2 ],
			"to": [ 11.7, 5.2, 6.8 ],
			"faces": {
				"down" : { "texture": "#sara" },
				"north": { "texture": "#sara" },
				"south": { "texture": "#sara" },
				"west" : { "texture": "#sara" },
				"east" : { "texture": "#sara" }
			}
		},
		{
			"name": "teasara_soko_e",
			"from": [ 13.3, 5, 5.2 ],
			"to": [ 13.5, 5.2, 6.8 ],
			"faces": {
				"down" : { "texture": "#sara" },
				"north": { "texture": "#sara" },
				"south": { "texture": "#sara" },
				"west" : { "texture": "#sara" },
				"east" : { "texture": "#sara" }
			}
		},

		{
            "name": "teasara",
            "from": [ 11.1, 5.2, 4.6 ],
            "to": [ 13.9, 5.4, 7.4 ],
            "faces": {
                "up" : { "texture": "#sara" },
                "down" : { "texture": "#sara" }
            }
        },
		{
            "name": "teasara_n___________________________",
            "from": [ 10.8, 5.2, 4.3 ],
            "to": [ 14.2, 5.4, 4.6 ],
            "faces": {
                "up" : { "texture": "#cup2" },
                "down" : { "texture": "#cup2" }
            }
        },
		{
            "name": "teasara_s",
            "from": [ 10.8, 5.2, 7.4 ],
            "to": [ 14.2, 5.4, 7.7 ],
            "faces": {
                "up" : { "texture": "#cup2" },
                "down" : { "texture": "#cup2" }
            }
        },
 		{
            "name": "teasara_e",
            "from": [ 10.8, 5.2, 4.6 ],
            "to": [ 11.1, 5.4, 7.4 ],
            "faces": {
                "up" : { "texture": "#cup2" },
                "down" : { "texture": "#cup2" }
            }
        },
		{
            "name": "teasara_w",
            "from": [ 13.9, 5.2, 4.6 ],
            "to": [ 14.2, 5.4, 7.4 ],
            "faces": {
                "up" : { "texture": "#cup2" },
                "down" : { "texture": "#cup2" }
            }
        },
		{
            "name": "teasara_n2___________________________",
            "from": [ 10.5, 5.2, 4.0 ],
            "to": [ 14.5, 5.4, 4.3 ],
            "faces": {
                "up" : { "texture": "#sara" },
                "down" : { "texture": "#sara" },
                "north": { "texture": "#sara" },
                "west" : { "texture": "#sara" },
				"east" : { "texture": "#sara" }
            }
        },
		{
            "name": "teasara_s2",
            "from": [ 10.5, 5.2, 7.7 ],
            "to": [ 14.5, 5.4, 8.0 ],
            "faces": {
                "up" : { "texture": "#sara" },
                "down" : { "texture": "#sara" },
                "south": { "texture": "#sara" },
                "west" : { "texture": "#sara" },
				"east" : { "texture": "#sara" }
            }
        },
 		{
            "name": "teasara_e2",
            "from": [ 10.5, 5.2, 4.3 ],
            "to": [ 10.8, 5.4, 7.7 ],
            "faces": {
                "up" : { "texture": "#sara" },
                "down" : { "texture": "#sara" },
                "west" : { "texture": "#sara" }
            }
        },
		{
            "name": "teasara_w2",
            "from": [ 14.2, 5.2, 4.3 ],
            "to": [ 14.5, 5.4, 7.7 ],
            "faces": {
                "up" : { "texture": "#sara" },
                "down" : { "texture": "#sara" },
				"east" : { "texture": "#sara" }
            }
        },

		{
			"name": "cup_soko",
			"from": [ 11.9, 5.4, 5.4 ],
			"to": [ 13.1, 5.6, 6.6 ],
			"faces": {
				"up" : { "texture": "#cup" },
				"down" : { "texture": "#cup" },
				"north": { "texture": "#cup" },
				"south": { "texture": "#cup" },
				"west" : { "texture": "#cup" },
				"east" : { "texture": "#cup" }
			}
		},
		{
			"name": "cup_n1_____________________________",
			"from": [ 11.7, 5.6, 5.2 ],
			"to": [ 13.3, 5.95, 5.4 ],
			"faces": {
				"up" : { "texture": "#cup" },
				"down" : { "texture": "#cup" },
				"north": { "texture": "#cup" },
				"south": { "texture": "#cup" },
				"west" : { "texture": "#cup" },
				"east" : { "texture": "#cup" }
			}
		},
		{
			"name": "cup_s1",
			"from": [ 11.7, 5.6, 6.6 ],
			"to": [ 13.3, 5.95, 6.8 ],
			"faces": {
				"up" : { "texture": "#cup" },
				"down" : { "texture": "#cup" },
				"north": { "texture": "#cup" },
				"south": { "texture": "#cup" },
				"west" : { "texture": "#cup" },
				"east" : { "texture": "#cup" }
			}
		},
		{
			"name": "cup_e1",
			"from": [ 13.1, 5.6, 5.4 ],
			"to": [ 13.3, 5.95, 6.6 ],
			"faces": {
				"up" : { "texture": "#cup" },
				"down" : { "texture": "#cup" },
				"west" : { "texture": "#cup" },
				"east" : { "texture": "#cup" }
			}
		},
		{
			"name": "cup_w1",
			"from": [ 11.7, 5.6, 5.4 ],
			"to": [ 11.9, 5.95, 6.6 ],
			"faces": {
				"up" : { "texture": "#cup" },
				"down" : { "texture": "#cup" },
				"west" : { "texture": "#cup" },
				"east" : { "texture": "#cup" }
			}
		},
		{
			"name": "cup_n2_____________________________",
			"from": [ 11.5, 5.95, 5 ],
			"to": [ 13.5, 6.3, 5.2 ],
			"faces": {
				"up" : { "texture": "#cup" },
				"down" : { "texture": "#cup" },
				"north": { "texture": "#cup" },
				"south": { "texture": "#cup" },
				"west" : { "texture": "#cup" },
				"east" : { "texture": "#cup" }
			}
		},
		{
			"name": "cup_s2",
			"from": [ 11.5, 5.95, 6.8 ],
			"to": [ 13.5, 6.3, 7 ],
			"faces": {
				"up" : { "texture": "#cup" },
				"down" : { "texture": "#cup" },
				"north": { "texture": "#cup" },
				"south": { "texture": "#cup" },
				"west" : { "texture": "#cup" },
				"east" : { "texture": "#cup" }
			}
		},
		{
			"name": "cup_e2",
			"from": [ 13.3, 5.95, 5.2 ],
			"to": [ 13.5, 6.3, 6.8 ],
			"faces": {
				"up" : { "texture": "#cup" },
				"down" : { "texture": "#cup" },
				"west" : { "texture": "#cup" },
				"east" : { "texture": "#cup" }
			}
		},
		{
			"name": "cup_w2",
			"from": [ 11.5, 5.95, 5.2 ],
			"to": [ 11.7, 6.3, 6.8 ],
			"faces": {
				"up" : { "texture": "#cup" },
				"down" : { "texture": "#cup" },
				"west" : { "texture": "#cup" },
				"east" : { "texture": "#cup" }
			}
		},
		{
			"name": "cup_n3_____________________________",
			"from": [ 11.3, 6.3, 4.8 ],
			"to": [ 13.7, 6.65, 5.0 ],
			"faces": {
				"up" : { "texture": "#cup" },
				"down" : { "texture": "#cup" },
				"north": { "texture": "#cup" },
				"south": { "texture": "#cup" },
				"west" : { "texture": "#cup" },
				"east" : { "texture": "#cup" }
			}
		},
		{
			"name": "cup_s3",
			"from": [ 11.3, 6.3, 7.0 ],
			"to": [ 13.7, 6.65, 7.2 ],
			"faces": {
				"up" : { "texture": "#cup" },
				"down" : { "texture": "#cup" },
				"north": { "texture": "#cup" },
				"south": { "texture": "#cup" },
				"west" : { "texture": "#cup" },
				"east" : { "texture": "#cup" }
			}
		},
		{
			"name": "cup_e3",
			"from": [ 13.5, 6.3, 5.0 ],
			"to": [ 13.7, 6.65, 7.0 ],
			"faces": {
				"up" : { "texture": "#cup" },
				"down" : { "texture": "#cup" },
				"west" : { "texture": "#cup" },
				"east" : { "texture": "#cup" }
			}
		},
		{
			"name": "cup_w3",
			"from": [ 11.3, 6.3, 5.0 ],
			"to": [ 11.5, 6.65, 7.0 ],
			"faces": {
				"up" : { "texture": "#cup" },
				"down" : { "texture": "#cup" },
				"west" : { "texture": "#cup" },
				"east" : { "texture": "#cup" }
			}
		},
		{
			"name": "cup_n4_____________________________",
			"from": [ 11.1, 6.65, 4.6 ],
			"to": [ 13.9, 7, 4.8 ],
			"faces": {
				"up" : { "texture": "#cup" },
				"down" : { "texture": "#cup" },
				"north": { "texture": "#cup2" },
				"south": { "texture": "#cup" },
				"west" : { "texture": "#cup2" },
				"east" : { "texture": "#cup2" }
			}
		},
		{
			"name": "cup_s4",
			"from": [ 11.1, 6.65, 7.2 ],
			"to": [ 13.9, 7, 7.4 ],
			"faces": {
				"up" : { "texture": "#cup" },
				"down" : { "texture": "#cup" },
				"north": { "texture": "#cup" },
				"south": { "texture": "#cup2" },
				"west" : { "texture": "#cup2" },
				"east" : { "texture": "#cup2" }
			}
		},
		{
			"name": "cup_e4",
			"from": [ 13.7, 6.65, 4.8 ],
			"to": [ 13.9, 7, 7.2 ],
			"faces": {
				"up" : { "texture": "#cup" },
				"down" : { "texture": "#cup" },
				"west" : { "texture": "#cup" },
				"east" : { "texture": "#cup2" }
			}
		},
		{
			"name": "cup_w4",
			"from": [ 11.1, 6.65, 4.8 ],
			"to": [ 11.3, 7, 7.2 ],
			"faces": {
				"up" : { "texture": "#cup" },
				"down" : { "texture": "#cup" },
				"west" : { "texture": "#cup2" },
				"east" : { "texture": "#cup" }
			}
		},
		{
			"name": "cup_totte_____________________________",
			"from": [ 13.9, 6.65, 5.85 ],
			"to": [ 14.3, 6.95, 6.15 ],
			"faces": {
				"up" : { "texture": "#cup" },
				"down" : { "texture": "#cup" },
				"north": { "texture": "#cup" },
				"south": { "texture": "#cup" },
				"east" : { "texture": "#cup" }
			}
		},
		{
			"name": "cup_totte",
			"from": [ 14.15, 5.95, 5.85 ],
			"to": [ 14.45, 6.65, 6.15 ],
			"faces": {
				"up" : { "texture": "#cup" },
				"down" : { "texture": "#cup" },
				"north": { "texture": "#cup" },
				"south": { "texture": "#cup" },
				"west" : { "texture": "#cup" },
				"east" : { "texture": "#cup" }
			}
		},
		{
			"name": "cup_totte",
			"from": [ 13.3, 5.65, 5.85 ],
			"to": [ 14.3, 5.95, 6.15 ],
			"faces": {
				"up" : { "texture": "#cup" },
				"down" : { "texture": "#cup" },
				"north": { "texture": "#cup" },
				"south": { "texture": "#cup" },
				"east" : { "texture": "#cup" }
			}
		},

    	{
			"name": "teasara_soko_n__________________________aaaaaaaaaaaaaaa",
			"from": [ 7.0, 5, 5.0 ],
			"to": [ 9.0, 5.2, 5.2 ],
			"faces": {
				"down" : { "texture": "#sara" },
				"north": { "texture": "#sara" },
				"south": { "texture": "#sara" },
				"west" : { "texture": "#sara" },
				"east" : { "texture": "#sara" }
			}
		},
		{
			"name": "teasara_soko_s",
			"from": [ 7.0, 5, 6.8 ],
			"to": [ 9.0, 5.2, 7.0 ],
			"faces": {
				"down" : { "texture": "#sara" },
				"north": { "texture": "#sara" },
				"south": { "texture": "#sara" },
				"west" : { "texture": "#sara" },
				"east" : { "texture": "#sara" }
			}
		},
		{
			"name": "teasara_soko_w",
			"from": [ 7.0, 5, 5.2 ],
			"to": [ 7.2, 5.2, 6.8 ],
			"faces": {
				"down" : { "texture": "#sara" },
				"north": { "texture": "#sara" },
				"south": { "texture": "#sara" },
				"west" : { "texture": "#sara" },
				"east" : { "texture": "#sara" }
			}
		},
		{
			"name": "teasara_soko_e",
			"from": [ 8.8, 5, 5.2 ],
			"to": [ 9.0, 5.2, 6.8 ],
			"faces": {
				"down" : { "texture": "#sara" },
				"north": { "texture": "#sara" },
				"south": { "texture": "#sara" },
				"west" : { "texture": "#sara" },
				"east" : { "texture": "#sara" }
			}
		},

		{
            "name": "teasara",
            "from": [ 6.6, 5.2, 4.6 ],
            "to": [ 9.4, 5.4, 7.4 ],
            "faces": {
                "up" : { "texture": "#sara" },
                "down" : { "texture": "#sara" }
            }
        },
		{
            "name": "teasara_n___________________________",
            "from": [ 6.3, 5.2, 4.3 ],
            "to": [ 9.7, 5.4, 4.6 ],
            "faces": {
                "up" : { "texture": "#cup2" },
                "down" : { "texture": "#cup2" }
            }
        },
		{
            "name": "teasara_s",
            "from": [ 6.3, 5.2, 7.4 ],
            "to": [ 9.7, 5.4, 7.7 ],
            "faces": {
                "up" : { "texture": "#cup2" },
                "down" : { "texture": "#cup2" }
            }
        },
 		{
            "name": "teasara_e",
            "from": [ 6.3, 5.2, 4.6 ],
            "to": [ 6.6, 5.4, 7.4 ],
            "faces": {
                "up" : { "texture": "#cup2" },
                "down" : { "texture": "#cup2" }
            }
        },
		{
            "name": "teasara_w",
            "from": [ 9.4, 5.2, 4.6 ],
            "to": [ 9.7, 5.4, 7.4 ],
            "faces": {
                "up" : { "texture": "#cup2" },
                "down" : { "texture": "#cup2" }
            }
        },
		{
            "name": "teasara_n2___________________________",
            "from": [ 6.0, 5.2, 4.0 ],
            "to": [ 10.0, 5.4, 4.3 ],
            "faces": {
                "up" : { "texture": "#sara" },
                "down" : { "texture": "#sara" },
                "north": { "texture": "#sara" },
                "west" : { "texture": "#sara" },
				"east" : { "texture": "#sara" }
            }
        },
		{
            "name": "teasara_s2",
            "from": [ 6.0, 5.2, 7.7 ],
            "to": [ 10.0, 5.4, 8.0 ],
            "faces": {
                "up" : { "texture": "#sara" },
                "down" : { "texture": "#sara" },
                "south": { "texture": "#sara" },
                "west" : { "texture": "#sara" },
				"east" : { "texture": "#sara" }
            }
        },
 		{
            "name": "teasara_e2",
            "from": [ 6.0, 5.2, 4.3 ],
            "to": [ 6.3, 5.4, 7.7 ],
            "faces": {
                "up" : { "texture": "#sara" },
                "down" : { "texture": "#sara" },
                "west" : { "texture": "#sara" }
            }
        },
		{
            "name": "teasara_w2",
            "from": [ 9.7, 5.2, 4.3 ],
            "to": [ 10.0, 5.4, 7.7 ],
            "faces": {
                "up" : { "texture": "#sara" },
                "down" : { "texture": "#sara" },
				"east" : { "texture": "#sara" }
            }
        },

		{
			"name": "cup_soko",
			"from": [ 7.4, 5.4, 5.4 ],
			"to": [ 8.6, 5.6, 6.6 ],
			"faces": {
				"up" : { "texture": "#cup" },
				"down" : { "texture": "#cup" },
				"north": { "texture": "#cup" },
				"south": { "texture": "#cup" },
				"west" : { "texture": "#cup" },
				"east" : { "texture": "#cup" }
			}
		},
		{
			"name": "cup_n1_____________________________",
			"from": [ 7.2, 5.6, 5.2 ],
			"to": [ 8.8, 5.95, 5.4 ],
			"faces": {
				"up" : { "texture": "#cup" },
				"down" : { "texture": "#cup" },
				"north": { "texture": "#cup" },
				"south": { "texture": "#cup" },
				"west" : { "texture": "#cup" },
				"east" : { "texture": "#cup" }
			}
		},
		{
			"name": "cup_s1",
			"from": [ 7.2, 5.6, 6.6 ],
			"to": [ 8.8, 5.95, 6.8 ],
			"faces": {
				"up" : { "texture": "#cup" },
				"down" : { "texture": "#cup" },
				"north": { "texture": "#cup" },
				"south": { "texture": "#cup" },
				"west" : { "texture": "#cup" },
				"east" : { "texture": "#cup" }
			}
		},
		{
			"name": "cup_e1",
			"from": [ 8.6, 5.6, 5.4 ],
			"to": [ 8.8, 5.95, 6.6 ],
			"faces": {
				"up" : { "texture": "#cup" },
				"down" : { "texture": "#cup" },
				"west" : { "texture": "#cup" },
				"east" : { "texture": "#cup" }
			}
		},
		{
			"name": "cup_w1",
			"from": [ 7.2, 5.6, 5.4 ],
			"to": [ 7.4, 5.95, 6.6 ],
			"faces": {
				"up" : { "texture": "#cup" },
				"down" : { "texture": "#cup" },
				"west" : { "texture": "#cup" },
				"east" : { "texture": "#cup" }
			}
		},
		{
			"name": "cup_n2_____________________________",
			"from": [ 7, 5.95, 5 ],
			"to": [ 9, 6.3, 5.2 ],
			"faces": {
				"up" : { "texture": "#cup" },
				"down" : { "texture": "#cup" },
				"north": { "texture": "#cup" },
				"south": { "texture": "#cup" },
				"west" : { "texture": "#cup" },
				"east" : { "texture": "#cup" }
			}
		},
		{
			"name": "cup_s2",
			"from": [ 7, 5.95, 6.8 ],
			"to": [ 9, 6.3, 7 ],
			"faces": {
				"up" : { "texture": "#cup" },
				"down" : { "texture": "#cup" },
				"north": { "texture": "#cup" },
				"south": { "texture": "#cup" },
				"west" : { "texture": "#cup" },
				"east" : { "texture": "#cup" }
			}
		},
		{
			"name": "cup_e2",
			"from": [ 8.8, 5.95, 5.2 ],
			"to": [ 9, 6.3, 6.8 ],
			"faces": {
				"up" : { "texture": "#cup" },
				"down" : { "texture": "#cup" },
				"west" : { "texture": "#cup" },
				"east" : { "texture": "#cup" }
			}
		},
		{
			"name": "cup_w2",
			"from": [ 7, 5.95, 5.2 ],
			"to": [ 7.2, 6.3, 6.8 ],
			"faces": {
				"up" : { "texture": "#cup" },
				"down" : { "texture": "#cup" },
				"west" : { "texture": "#cup" },
				"east" : { "texture": "#cup" }
			}
		},
		{
			"name": "cup_n3_____________________________",
			"from": [ 6.8, 6.3, 4.8 ],
			"to": [ 9.2, 6.65, 5.0 ],
			"faces": {
				"up" : { "texture": "#cup" },
				"down" : { "texture": "#cup" },
				"north": { "texture": "#cup" },
				"south": { "texture": "#cup" },
				"west" : { "texture": "#cup" },
				"east" : { "texture": "#cup" }
			}
		},
		{
			"name": "cup_s3",
			"from": [ 6.8, 6.3, 7.0 ],
			"to": [ 9.2, 6.65, 7.2 ],
			"faces": {
				"up" : { "texture": "#cup" },
				"down" : { "texture": "#cup" },
				"north": { "texture": "#cup" },
				"south": { "texture": "#cup" },
				"west" : { "texture": "#cup" },
				"east" : { "texture": "#cup" }
			}
		},
		{
			"name": "cup_e3",
			"from": [ 9.0, 6.3, 5.0 ],
			"to": [ 9.2, 6.65, 7.0 ],
			"faces": {
				"up" : { "texture": "#cup" },
				"down" : { "texture": "#cup" },
				"west" : { "texture": "#cup" },
				"east" : { "texture": "#cup" }
			}
		},
		{
			"name": "cup_w3",
			"from": [ 6.8, 6.3, 5.0 ],
			"to": [ 7.0, 6.65, 7.0 ],
			"faces": {
				"up" : { "texture": "#cup" },
				"down" : { "texture": "#cup" },
				"west" : { "texture": "#cup" },
				"east" : { "texture": "#cup" }
			}
		},
		{
			"name": "cup_n4_____________________________",
			"from": [ 6.6, 6.65, 4.6 ],
			"to": [ 9.4, 7, 4.8 ],
			"faces": {
				"up" : { "texture": "#cup" },
				"down" : { "texture": "#cup" },
				"north": { "texture": "#cup2" },
				"south": { "texture": "#cup" },
				"west" : { "texture": "#cup2" },
				"east" : { "texture": "#cup2" }
			}
		},
		{
			"name": "cup_s4",
			"from": [ 6.6, 6.65, 7.2 ],
			"to": [ 9.4, 7, 7.4 ],
			"faces": {
				"up" : { "texture": "#cup" },
				"down" : { "texture": "#cup" },
				"north": { "texture": "#cup" },
				"south": { "texture": "#cup2" },
				"west" : { "texture": "#cup2" },
				"east" : { "texture": "#cup2" }
			}
		},
		{
			"name": "cup_e4",
			"from": [ 9.2, 6.65, 4.8 ],
			"to": [ 9.4, 7, 7.2 ],
			"faces": {
				"up" : { "texture": "#cup" },
				"down" : { "texture": "#cup" },
				"west" : { "texture": "#cup" },
				"east" : { "texture": "#cup2" }
			}
		},
		{
			"name": "cup_w4",
			"from": [ 6.6, 6.65, 4.8 ],
			"to": [ 6.8, 7, 7.2 ],
			"faces": {
				"up" : { "texture": "#cup" },
				"down" : { "texture": "#cup" },
				"west" : { "texture": "#cup2" },
				"east" : { "texture": "#cup" }
			}
		},
		{
			"name": "cup_totte_____________________________",
			"from": [ 9.4, 6.65, 5.85 ],
			"to": [ 9.8, 6.95, 6.15 ],
			"faces": {
				"up" : { "texture": "#cup" },
				"down" : { "texture": "#cup" },
				"north": { "texture": "#cup" },
				"south": { "texture": "#cup" },
				"east" : { "texture": "#cup" }
			}
		},
		{
			"name": "cup_totte",
			"from": [ 9.65, 5.95, 5.85 ],
			"to": [ 9.95, 6.65, 6.15 ],
			"faces": {
				"up" : { "texture": "#cup" },
				"down" : { "texture": "#cup" },
				"north": { "texture": "#cup" },
				"south": { "texture": "#cup" },
				"west" : { "texture": "#cup" },
				"east" : { "texture": "#cup" }
			}
		},
		{
			"name": "cup_totte",
			"from": [ 8.8, 5.65, 5.85 ],
			"to": [ 9.8, 5.95, 6.15 ],
			"faces": {
				"up" : { "texture": "#cup" },
				"down" : { "texture": "#cup" },
				"north": { "texture": "#cup" },
				"south": { "texture": "#cup" },
				"east" : { "texture": "#cup" }
			}
		},

    	{
			"name": "teasara_soko_n__________________________44444444444444",
			"from": [ 2.5, 5, 5.0 ],
			"to": [ 4.5, 5.2, 5.2 ],
			"faces": {
				"down" : { "texture": "#sara" },
				"north": { "texture": "#sara" },
				"south": { "texture": "#sara" },
				"west" : { "texture": "#sara" },
				"east" : { "texture": "#sara" }
			}
		},
		{
			"name": "teasara_soko_s",
			"from": [ 2.5, 5, 6.8 ],
			"to": [ 4.5, 5.2, 7.0 ],
			"faces": {
				"down" : { "texture": "#sara" },
				"north": { "texture": "#sara" },
				"south": { "texture": "#sara" },
				"west" : { "texture": "#sara" },
				"east" : { "texture": "#sara" }
			}
		},
		{
			"name": "teasara_soko_w",
			"from": [ 2.5, 5, 5.2 ],
			"to": [ 2.7, 5.2, 6.8 ],
			"faces": {
				"down" : { "texture": "#sara" },
				"north": { "texture": "#sara" },
				"south": { "texture": "#sara" },
				"west" : { "texture": "#sara" },
				"east" : { "texture": "#sara" }
			}
		},
		{
			"name": "teasara_soko_e",
			"from": [ 4.3, 5, 5.2 ],
			"to": [ 4.5, 5.2, 6.8 ],
			"faces": {
				"down" : { "texture": "#sara" },
				"north": { "texture": "#sara" },
				"south": { "texture": "#sara" },
				"west" : { "texture": "#sara" },
				"east" : { "texture": "#sara" }
			}
		},

		{
            "name": "teasara",
            "from": [ 2.1, 5.2, 4.6 ],
            "to": [ 4.9, 5.4, 7.4 ],
            "faces": {
                "up" : { "texture": "#sara" },
                "down" : { "texture": "#sara" }
            }
        },
		{
            "name": "teasara_n___________________________",
            "from": [ 1.8, 5.2, 4.3 ],
            "to": [ 5.2, 5.4, 4.6 ],
            "faces": {
                "up" : { "texture": "#cup2" },
                "down" : { "texture": "#cup2" }
            }
        },
		{
            "name": "teasara_s",
            "from": [ 1.8, 5.2, 7.4 ],
            "to": [ 5.2, 5.4, 7.7 ],
            "faces": {
                "up" : { "texture": "#cup2" },
                "down" : { "texture": "#cup2" }
            }
        },
 		{
            "name": "teasara_e",
            "from": [ 1.8, 5.2, 4.6 ],
            "to": [ 2.1, 5.4, 7.4 ],
            "faces": {
                "up" : { "texture": "#cup2" },
                "down" : { "texture": "#cup2" }
            }
        },
		{
            "name": "teasara_w",
            "from": [ 4.9, 5.2, 4.6 ],
            "to": [ 5.2, 5.4, 7.4 ],
            "faces": {
                "up" : { "texture": "#cup2" },
                "down" : { "texture": "#cup2" }
            }
        },
		{
            "name": "teasara_n2___________________________",
            "from": [ 1.5, 5.2, 4.0 ],
            "to": [ 5.5, 5.4, 4.3 ],
            "faces": {
                "up" : { "texture": "#sara" },
                "down" : { "texture": "#sara" },
                "north": { "texture": "#sara" },
                "west" : { "texture": "#sara" },
				"east" : { "texture": "#sara" }
            }
        },
		{
            "name": "teasara_s2",
            "from": [ 1.5, 5.2, 7.7 ],
            "to": [ 5.5, 5.4, 8.0 ],
            "faces": {
                "up" : { "texture": "#sara" },
                "down" : { "texture": "#sara" },
                "south": { "texture": "#sara" },
                "west" : { "texture": "#sara" },
				"east" : { "texture": "#sara" }
            }
        },
 		{
            "name": "teasara_e2",
            "from": [ 1.5, 5.2, 4.3 ],
            "to": [ 1.8, 5.4, 7.7 ],
            "faces": {
                "up" : { "texture": "#sara" },
                "down" : { "texture": "#sara" },
                "west" : { "texture": "#sara" }
            }
        },
		{
            "name": "teasara_w2",
            "from": [ 5.2, 5.2, 4.3 ],
            "to": [ 5.5, 5.4, 7.7 ],
            "faces": {
                "up" : { "texture": "#sara" },
                "down" : { "texture": "#sara" },
				"east" : { "texture": "#sara" }
            }
        },

		{
			"name": "cup_soko",
			"from": [ 2.9, 5.4, 5.4 ],
			"to": [ 4.1, 5.6, 6.6 ],
			"faces": {
				"up" : { "texture": "#cup" },
				"down" : { "texture": "#cup" },
				"north": { "texture": "#cup" },
				"south": { "texture": "#cup" },
				"west" : { "texture": "#cup" },
				"east" : { "texture": "#cup" }
			}
		},
		{
			"name": "cup_n1_____________________________",
			"from": [ 2.7, 5.6, 5.2 ],
			"to": [ 4.3, 5.95, 5.4 ],
			"faces": {
				"up" : { "texture": "#cup" },
				"down" : { "texture": "#cup" },
				"north": { "texture": "#cup" },
				"south": { "texture": "#cup" },
				"west" : { "texture": "#cup" },
				"east" : { "texture": "#cup" }
			}
		},
		{
			"name": "cup_s1",
			"from": [ 2.7, 5.6, 6.6 ],
			"to": [ 4.3, 5.95, 6.8 ],
			"faces": {
				"up" : { "texture": "#cup" },
				"down" : { "texture": "#cup" },
				"north": { "texture": "#cup" },
				"south": { "texture": "#cup" },
				"west" : { "texture": "#cup" },
				"east" : { "texture": "#cup" }
			}
		},
		{
			"name": "cup_e1",
			"from": [ 4.1, 5.6, 5.4 ],
			"to": [ 4.3, 5.95, 6.6 ],
			"faces": {
				"up" : { "texture": "#cup" },
				"down" : { "texture": "#cup" },
				"west" : { "texture": "#cup" },
				"east" : { "texture": "#cup" }
			}
		},
		{
			"name": "cup_w1",
			"from": [ 2.7, 5.6, 5.4 ],
			"to": [ 2.9, 5.95, 6.6 ],
			"faces": {
				"up" : { "texture": "#cup" },
				"down" : { "texture": "#cup" },
				"west" : { "texture": "#cup" },
				"east" : { "texture": "#cup" }
			}
		},
		{
			"name": "cup_n2_____________________________",
			"from": [ 2.5, 5.95, 5 ],
			"to": [ 4.5, 6.3, 5.2 ],
			"faces": {
				"up" : { "texture": "#cup" },
				"down" : { "texture": "#cup" },
				"north": { "texture": "#cup" },
				"south": { "texture": "#cup" },
				"west" : { "texture": "#cup" },
				"east" : { "texture": "#cup" }
			}
		},
		{
			"name": "cup_s2",
			"from": [ 2.5, 5.95, 6.8 ],
			"to": [ 4.5, 6.3, 7 ],
			"faces": {
				"up" : { "texture": "#cup" },
				"down" : { "texture": "#cup" },
				"north": { "texture": "#cup" },
				"south": { "texture": "#cup" },
				"west" : { "texture": "#cup" },
				"east" : { "texture": "#cup" }
			}
		},
		{
			"name": "cup_e2",
			"from": [ 4.3, 5.95, 5.2 ],
			"to": [ 4.5, 6.3, 6.8 ],
			"faces": {
				"up" : { "texture": "#cup" },
				"down" : { "texture": "#cup" },
				"west" : { "texture": "#cup" },
				"east" : { "texture": "#cup" }
			}
		},
		{
			"name": "cup_w2",
			"from": [ 2.5, 5.95, 5.2 ],
			"to": [ 2.7, 6.3, 6.8 ],
			"faces": {
				"up" : { "texture": "#cup" },
				"down" : { "texture": "#cup" },
				"west" : { "texture": "#cup" },
				"east" : { "texture": "#cup" }
			}
		},
		{
			"name": "cup_n3_____________________________",
			"from": [ 2.3, 6.3, 4.8 ],
			"to": [ 4.7, 6.65, 5.0 ],
			"faces": {
				"up" : { "texture": "#cup" },
				"down" : { "texture": "#cup" },
				"north": { "texture": "#cup" },
				"south": { "texture": "#cup" },
				"west" : { "texture": "#cup" },
				"east" : { "texture": "#cup" }
			}
		},
		{
			"name": "cup_s3",
			"from": [ 2.3, 6.3, 7.0 ],
			"to": [ 4.7, 6.65, 7.2 ],
			"faces": {
				"up" : { "texture": "#cup" },
				"down" : { "texture": "#cup" },
				"north": { "texture": "#cup" },
				"south": { "texture": "#cup" },
				"west" : { "texture": "#cup" },
				"east" : { "texture": "#cup" }
			}
		},
		{
			"name": "cup_e3",
			"from": [ 4.5, 6.3, 5.0 ],
			"to": [ 4.7, 6.65, 7.0 ],
			"faces": {
				"up" : { "texture": "#cup" },
				"down" : { "texture": "#cup" },
				"west" : { "texture": "#cup" },
				"east" : { "texture": "#cup" }
			}
		},
		{
			"name": "cup_w3",
			"from": [ 2.3, 6.3, 5.0 ],
			"to": [ 2.5, 6.65, 7.0 ],
			"faces": {
				"up" : { "texture": "#cup" },
				"down" : { "texture": "#cup" },
				"west" : { "texture": "#cup" },
				"east" : { "texture": "#cup" }
			}
		},
		{
			"name": "cup_n4_____________________________",
			"from": [ 2.1, 6.65, 4.6 ],
			"to": [ 4.9, 7, 4.8 ],
			"faces": {
				"up" : { "texture": "#cup" },
				"down" : { "texture": "#cup" },
				"north": { "texture": "#cup2" },
				"south": { "texture": "#cup" },
				"west" : { "texture": "#cup2" },
				"east" : { "texture": "#cup2" }
			}
		},
		{
			"name": "cup_s4",
			"from": [ 2.1, 6.65, 7.2 ],
			"to": [ 4.9, 7, 7.4 ],
			"faces": {
				"up" : { "texture": "#cup" },
				"down" : { "texture": "#cup" },
				"north": { "texture": "#cup" },
				"south": { "texture": "#cup2" },
				"west" : { "texture": "#cup2" },
				"east" : { "texture": "#cup2" }
			}
		},
		{
			"name": "cup_e4",
			"from": [ 4.7, 6.65, 4.8 ],
			"to": [ 4.9, 7, 7.2 ],
			"faces": {
				"up" : { "texture": "#cup" },
				"down" : { "texture": "#cup" },
				"west" : { "texture": "#cup" },
				"east" : { "texture": "#cup2" }
			}
		},
		{
			"name": "cup_w4",
			"from": [ 2.1, 6.65, 4.8 ],
			"to": [ 2.3, 7, 7.2 ],
			"faces": {
				"up" : { "texture": "#cup" },
				"down" : { "texture": "#cup" },
				"west" : { "texture": "#cup2" },
				"east" : { "texture": "#cup" }
			}
		},
		{
			"name": "cup_totte_____________________________",
			"from": [ 4.9, 6.65, 5.85 ],
			"to": [ 5.3, 6.95, 6.15 ],
			"faces": {
				"up" : { "texture": "#cup" },
				"down" : { "texture": "#cup" },
				"north": { "texture": "#cup" },
				"south": { "texture": "#cup" },
				"east" : { "texture": "#cup" }
			}
		},
		{
			"name": "cup_totte",
			"from": [ 5.15, 5.95, 5.85 ],
			"to": [ 5.45, 6.65, 6.15 ],
			"faces": {
				"up" : { "texture": "#cup" },
				"down" : { "texture": "#cup" },
				"north": { "texture": "#cup" },
				"south": { "texture": "#cup" },
				"west" : { "texture": "#cup" },
				"east" : { "texture": "#cup" }
			}
		},
		{
			"name": "cup_totte",
			"from": [ 4.3, 5.65, 5.85 ],
			"to": [ 5.3, 5.95, 6.15 ],
			"faces": {
				"up" : { "texture": "#cup" },
				"down" : { "texture": "#cup" },
				"north": { "texture": "#cup" },
				"south": { "texture": "#cup" },
				"east" : { "texture": "#cup" }
			}
		},


    	{
			"name": "teasara_soko_n__________________________333333333333333",
			"from": [ 11.5, 1, 5.0 ],
			"to": [ 13.5, 1.2, 5.2 ],
			"faces": {
				"down" : { "texture": "#sara" },
				"north": { "texture": "#sara" },
				"south": { "texture": "#sara" },
				"west" : { "texture": "#sara" },
				"east" : { "texture": "#sara" }
			}
		},
		{
			"name": "teasara_soko_s",
			"from": [ 11.5, 1, 6.8 ],
			"to": [ 13.5, 1.2, 7.0 ],
			"faces": {
				"down" : { "texture": "#sara" },
				"north": { "texture": "#sara" },
				"south": { "texture": "#sara" },
				"west" : { "texture": "#sara" },
				"east" : { "texture": "#sara" }
			}
		},
		{
			"name": "teasara_soko_w",
			"from": [ 11.5, 1, 5.2 ],
			"to": [ 11.7, 1.2, 6.8 ],
			"faces": {
				"down" : { "texture": "#sara" },
				"north": { "texture": "#sara" },
				"south": { "texture": "#sara" },
				"west" : { "texture": "#sara" },
				"east" : { "texture": "#sara" }
			}
		},
		{
			"name": "teasara_soko_e",
			"from": [ 13.3, 1, 5.2 ],
			"to": [ 13.5, 1.2, 6.8 ],
			"faces": {
				"down" : { "texture": "#sara" },
				"north": { "texture": "#sara" },
				"south": { "texture": "#sara" },
				"west" : { "texture": "#sara" },
				"east" : { "texture": "#sara" }
			}
		},

		{
            "name": "teasara",
            "from": [ 11.1, 1.2, 4.6 ],
            "to": [ 13.9, 1.4, 7.4 ],
            "faces": {
                "up" : { "texture": "#sara" },
                "down" : { "texture": "#sara" }
            }
        },
		{
            "name": "teasara_n___________________________",
            "from": [ 10.8, 1.2, 4.3 ],
            "to": [ 14.2, 1.4, 4.6 ],
            "faces": {
                "up" : { "texture": "#cup2" },
                "down" : { "texture": "#cup2" }
            }
        },
		{
            "name": "teasara_s",
            "from": [ 10.8, 1.2, 7.4 ],
            "to": [ 14.2, 1.4, 7.7 ],
            "faces": {
                "up" : { "texture": "#cup2" },
                "down" : { "texture": "#cup2" }
            }
        },
 		{
            "name": "teasara_e",
            "from": [ 10.8, 1.2, 4.6 ],
            "to": [ 11.1, 1.4, 7.4 ],
            "faces": {
                "up" : { "texture": "#cup2" },
                "down" : { "texture": "#cup2" }
            }
        },
		{
            "name": "teasara_w",
            "from": [ 13.9, 1.2, 4.6 ],
            "to": [ 14.2, 1.4, 7.4 ],
            "faces": {
                "up" : { "texture": "#cup2" },
                "down" : { "texture": "#cup2" }
            }
        },
		{
            "name": "teasara_n2___________________________",
            "from": [ 10.5, 1.2, 4.0 ],
            "to": [ 14.5, 1.4, 4.3 ],
            "faces": {
                "up" : { "texture": "#sara" },
                "down" : { "texture": "#sara" },
                "north": { "texture": "#sara" },
                "west" : { "texture": "#sara" },
				"east" : { "texture": "#sara" }
            }
        },
		{
            "name": "teasara_s2",
            "from": [ 10.5, 1.2, 7.7 ],
            "to": [ 14.5, 1.4, 8.0 ],
            "faces": {
                "up" : { "texture": "#sara" },
                "down" : { "texture": "#sara" },
                "south": { "texture": "#sara" },
                "west" : { "texture": "#sara" },
				"east" : { "texture": "#sara" }
            }
        },
 		{
            "name": "teasara_e2",
            "from": [ 10.5, 1.2, 4.3 ],
            "to": [ 10.8, 1.4, 7.7 ],
            "faces": {
                "up" : { "texture": "#sara" },
                "down" : { "texture": "#sara" },
                "west" : { "texture": "#sara" }
            }
        },
		{
            "name": "teasara_w2",
            "from": [ 14.2, 1.2, 4.3 ],
            "to": [ 14.5, 1.4, 7.7 ],
            "faces": {
                "up" : { "texture": "#sara" },
                "down" : { "texture": "#sara" },
				"east" : { "texture": "#sara" }
            }
        },

		{
			"name": "cup_soko",
			"from": [ 11.9, 1.4, 5.4 ],
			"to": [ 13.1, 1.6, 6.6 ],
			"faces": {
				"up" : { "texture": "#cup" },
				"down" : { "texture": "#cup" },
				"north": { "texture": "#cup" },
				"south": { "texture": "#cup" },
				"west" : { "texture": "#cup" },
				"east" : { "texture": "#cup" }
			}
		},
		{
			"name": "cup_n1_____________________________",
			"from": [ 11.7, 1.6, 5.2 ],
			"to": [ 13.3, 1.95, 5.4 ],
			"faces": {
				"up" : { "texture": "#cup" },
				"down" : { "texture": "#cup" },
				"north": { "texture": "#cup" },
				"south": { "texture": "#cup" },
				"west" : { "texture": "#cup" },
				"east" : { "texture": "#cup" }
			}
		},
		{
			"name": "cup_s1",
			"from": [ 11.7, 1.6, 6.6 ],
			"to": [ 13.3, 1.95, 6.8 ],
			"faces": {
				"up" : { "texture": "#cup" },
				"down" : { "texture": "#cup" },
				"north": { "texture": "#cup" },
				"south": { "texture": "#cup" },
				"west" : { "texture": "#cup" },
				"east" : { "texture": "#cup" }
			}
		},
		{
			"name": "cup_e1",
			"from": [ 13.1, 1.6, 5.4 ],
			"to": [ 13.3, 1.95, 6.6 ],
			"faces": {
				"up" : { "texture": "#cup" },
				"down" : { "texture": "#cup" },
				"west" : { "texture": "#cup" },
				"east" : { "texture": "#cup" }
			}
		},
		{
			"name": "cup_w1",
			"from": [ 11.7, 1.6, 5.4 ],
			"to": [ 11.9, 1.95, 6.6 ],
			"faces": {
				"up" : { "texture": "#cup" },
				"down" : { "texture": "#cup" },
				"west" : { "texture": "#cup" },
				"east" : { "texture": "#cup" }
			}
		},
		{
			"name": "cup_n2_____________________________",
			"from": [ 11.5, 1.95, 5 ],
			"to": [ 13.5, 2.3, 5.2 ],
			"faces": {
				"up" : { "texture": "#cup" },
				"down" : { "texture": "#cup" },
				"north": { "texture": "#cup" },
				"south": { "texture": "#cup" },
				"west" : { "texture": "#cup" },
				"east" : { "texture": "#cup" }
			}
		},
		{
			"name": "cup_s2",
			"from": [ 11.5, 1.95, 6.8 ],
			"to": [ 13.5, 2.3, 7 ],
			"faces": {
				"up" : { "texture": "#cup" },
				"down" : { "texture": "#cup" },
				"north": { "texture": "#cup" },
				"south": { "texture": "#cup" },
				"west" : { "texture": "#cup" },
				"east" : { "texture": "#cup" }
			}
		},
		{
			"name": "cup_e2",
			"from": [ 13.3, 1.95, 5.2 ],
			"to": [ 13.5, 2.3, 6.8 ],
			"faces": {
				"up" : { "texture": "#cup" },
				"down" : { "texture": "#cup" },
				"west" : { "texture": "#cup" },
				"east" : { "texture": "#cup" }
			}
		},
		{
			"name": "cup_w2",
			"from": [ 11.5, 1.95, 5.2 ],
			"to": [ 11.7, 2.3, 6.8 ],
			"faces": {
				"up" : { "texture": "#cup" },
				"down" : { "texture": "#cup" },
				"west" : { "texture": "#cup" },
				"east" : { "texture": "#cup" }
			}
		},
		{
			"name": "cup_n3_____________________________",
			"from": [ 11.3, 2.3, 4.8 ],
			"to": [ 13.7, 2.65, 5.0 ],
			"faces": {
				"up" : { "texture": "#cup" },
				"down" : { "texture": "#cup" },
				"north": { "texture": "#cup" },
				"south": { "texture": "#cup" },
				"west" : { "texture": "#cup" },
				"east" : { "texture": "#cup" }
			}
		},
		{
			"name": "cup_s3",
			"from": [ 11.3, 2.3, 7.0 ],
			"to": [ 13.7, 2.65, 7.2 ],
			"faces": {
				"up" : { "texture": "#cup" },
				"down" : { "texture": "#cup" },
				"north": { "texture": "#cup" },
				"south": { "texture": "#cup" },
				"west" : { "texture": "#cup" },
				"east" : { "texture": "#cup" }
			}
		},
		{
			"name": "cup_e3",
			"from": [ 13.5, 2.3, 5.0 ],
			"to": [ 13.7, 2.65, 7.0 ],
			"faces": {
				"up" : { "texture": "#cup" },
				"down" : { "texture": "#cup" },
				"west" : { "texture": "#cup" },
				"east" : { "texture": "#cup" }
			}
		},
		{
			"name": "cup_w3",
			"from": [ 11.3, 2.3, 5.0 ],
			"to": [ 11.5, 2.65, 7.0 ],
			"faces": {
				"up" : { "texture": "#cup" },
				"down" : { "texture": "#cup" },
				"west" : { "texture": "#cup" },
				"east" : { "texture": "#cup" }
			}
		},
		{
			"name": "cup_n4_____________________________",
			"from": [ 11.1, 2.65, 4.6 ],
			"to": [ 13.9, 3, 4.8 ],
			"faces": {
				"up" : { "texture": "#cup" },
				"down" : { "texture": "#cup" },
				"north": { "texture": "#cup2" },
				"south": { "texture": "#cup" },
				"west" : { "texture": "#cup2" },
				"east" : { "texture": "#cup2" }
			}
		},
		{
			"name": "cup_s4",
			"from": [ 11.1, 2.65, 7.2 ],
			"to": [ 13.9, 3, 7.4 ],
			"faces": {
				"up" : { "texture": "#cup" },
				"down" : { "texture": "#cup" },
				"north": { "texture": "#cup" },
				"south": { "texture": "#cup2" },
				"west" : { "texture": "#cup2" },
				"east" : { "texture": "#cup2" }
			}
		},
		{
			"name": "cup_e4",
			"from": [ 13.7, 2.65, 4.8 ],
			"to": [ 13.9, 3, 7.2 ],
			"faces": {
				"up" : { "texture": "#cup" },
				"down" : { "texture": "#cup" },
				"west" : { "texture": "#cup" },
				"east" : { "texture": "#cup2" }
			}
		},
		{
			"name": "cup_w4",
			"from": [ 11.1, 2.65, 4.8 ],
			"to": [ 11.3, 3, 7.2 ],
			"faces": {
				"up" : { "texture": "#cup" },
				"down" : { "texture": "#cup" },
				"west" : { "texture": "#cup2" },
				"east" : { "texture": "#cup" }
			}
		},
		{
			"name": "cup_totte_____________________________",
			"from": [ 13.9, 2.65, 5.85 ],
			"to": [ 14.3, 2.95, 6.15 ],
			"faces": {
				"up" : { "texture": "#cup" },
				"down" : { "texture": "#cup" },
				"north": { "texture": "#cup" },
				"south": { "texture": "#cup" },
				"east" : { "texture": "#cup" }
			}
		},
		{
			"name": "cup_totte",
			"from": [ 14.15, 1.95, 5.85 ],
			"to": [ 14.45, 2.65, 6.15 ],
			"faces": {
				"up" : { "texture": "#cup" },
				"down" : { "texture": "#cup" },
				"north": { "texture": "#cup" },
				"south": { "texture": "#cup" },
				"west" : { "texture": "#cup" },
				"east" : { "texture": "#cup" }
			}
		},
		{
			"name": "cup_totte",
			"from": [ 13.3, 1.65, 5.85 ],
			"to": [ 14.3, 1.95, 6.15 ],
			"faces": {
				"up" : { "texture": "#cup" },
				"down" : { "texture": "#cup" },
				"north": { "texture": "#cup" },
				"south": { "texture": "#cup" },
				"east" : { "texture": "#cup" }
			}
		},

    	{
			"name": "teasara_soko_n__________________________222222222222222",
			"from": [ 7.0, 1, 5.0 ],
			"to": [ 9.0, 1.2, 5.2 ],
			"faces": {
				"down" : { "texture": "#sara" },
				"north": { "texture": "#sara" },
				"south": { "texture": "#sara" },
				"west" : { "texture": "#sara" },
				"east" : { "texture": "#sara" }
			}
		},
		{
			"name": "teasara_soko_s",
			"from": [ 7.0, 1, 6.8 ],
			"to": [ 9.0, 1.2, 7.0 ],
			"faces": {
				"down" : { "texture": "#sara" },
				"north": { "texture": "#sara" },
				"south": { "texture": "#sara" },
				"west" : { "texture": "#sara" },
				"east" : { "texture": "#sara" }
			}
		},
		{
			"name": "teasara_soko_w",
			"from": [ 7.0, 1, 5.2 ],
			"to": [ 7.2, 1.2, 6.8 ],
			"faces": {
				"down" : { "texture": "#sara" },
				"north": { "texture": "#sara" },
				"south": { "texture": "#sara" },
				"west" : { "texture": "#sara" },
				"east" : { "texture": "#sara" }
			}
		},
		{
			"name": "teasara_soko_e",
			"from": [ 8.8, 1, 5.2 ],
			"to": [ 9.0, 1.2, 6.8 ],
			"faces": {
				"down" : { "texture": "#sara" },
				"north": { "texture": "#sara" },
				"south": { "texture": "#sara" },
				"west" : { "texture": "#sara" },
				"east" : { "texture": "#sara" }
			}
		},

		{
            "name": "teasara",
            "from": [ 6.6, 1.2, 4.6 ],
            "to": [ 9.4, 1.4, 7.4 ],
            "faces": {
                "up" : { "texture": "#sara" },
                "down" : { "texture": "#sara" }
            }
        },
		{
            "name": "teasara_n___________________________",
            "from": [ 6.3, 1.2, 4.3 ],
            "to": [ 9.7, 1.4, 4.6 ],
            "faces": {
                "up" : { "texture": "#cup2" },
                "down" : { "texture": "#cup2" }
            }
        },
		{
            "name": "teasara_s",
            "from": [ 6.3, 1.2, 7.4 ],
            "to": [ 9.7, 1.4, 7.7 ],
            "faces": {
                "up" : { "texture": "#cup2" },
                "down" : { "texture": "#cup2" }
            }
        },
 		{
            "name": "teasara_e",
            "from": [ 6.3, 1.2, 4.6 ],
            "to": [ 6.6, 1.4, 7.4 ],
            "faces": {
                "up" : { "texture": "#cup2" },
                "down" : { "texture": "#cup2" }
            }
        },
		{
            "name": "teasara_w",
            "from": [ 9.4, 1.2, 4.6 ],
            "to": [ 9.7, 1.4, 7.4 ],
            "faces": {
                "up" : { "texture": "#cup2" },
                "down" : { "texture": "#cup2" }
            }
        },
		{
            "name": "teasara_n2___________________________",
            "from": [ 6.0, 1.2, 4.0 ],
            "to": [ 10.0, 1.4, 4.3 ],
            "faces": {
                "up" : { "texture": "#sara" },
                "down" : { "texture": "#sara" },
                "north": { "texture": "#sara" },
                "west" : { "texture": "#sara" },
				"east" : { "texture": "#sara" }
            }
        },
		{
            "name": "teasara_s2",
            "from": [ 6.0, 1.2, 7.7 ],
            "to": [ 10.0, 1.4, 8.0 ],
            "faces": {
                "up" : { "texture": "#sara" },
                "down" : { "texture": "#sara" },
                "south": { "texture": "#sara" },
                "west" : { "texture": "#sara" },
				"east" : { "texture": "#sara" }
            }
        },
 		{
            "name": "teasara_e2",
            "from": [ 6.0, 1.2, 4.3 ],
            "to": [ 6.3, 1.4, 7.7 ],
            "faces": {
                "up" : { "texture": "#sara" },
                "down" : { "texture": "#sara" },
                "west" : { "texture": "#sara" }
            }
        },
		{
            "name": "teasara_w2",
            "from": [ 9.7, 1.2, 4.3 ],
            "to": [ 10.0, 1.4, 7.7 ],
            "faces": {
                "up" : { "texture": "#sara" },
                "down" : { "texture": "#sara" },
				"east" : { "texture": "#sara" }
            }
        },

		{
			"name": "cup_soko",
			"from": [ 7.4, 1.4, 5.4 ],
			"to": [ 8.6, 1.6, 6.6 ],
			"faces": {
				"up" : { "texture": "#cup" },
				"down" : { "texture": "#cup" },
				"north": { "texture": "#cup" },
				"south": { "texture": "#cup" },
				"west" : { "texture": "#cup" },
				"east" : { "texture": "#cup" }
			}
		},
		{
			"name": "cup_n1_____________________________",
			"from": [ 7.2, 1.6, 5.2 ],
			"to": [ 8.8, 1.95, 5.4 ],
			"faces": {
				"up" : { "texture": "#cup" },
				"down" : { "texture": "#cup" },
				"north": { "texture": "#cup" },
				"south": { "texture": "#cup" },
				"west" : { "texture": "#cup" },
				"east" : { "texture": "#cup" }
			}
		},
		{
			"name": "cup_s1",
			"from": [ 7.2, 1.6, 6.6 ],
			"to": [ 8.8, 1.95, 6.8 ],
			"faces": {
				"up" : { "texture": "#cup" },
				"down" : { "texture": "#cup" },
				"north": { "texture": "#cup" },
				"south": { "texture": "#cup" },
				"west" : { "texture": "#cup" },
				"east" : { "texture": "#cup" }
			}
		},
		{
			"name": "cup_e1",
			"from": [ 8.6, 1.6, 5.4 ],
			"to": [ 8.8, 1.95, 6.6 ],
			"faces": {
				"up" : { "texture": "#cup" },
				"down" : { "texture": "#cup" },
				"west" : { "texture": "#cup" },
				"east" : { "texture": "#cup" }
			}
		},
		{
			"name": "cup_w1",
			"from": [ 7.2, 1.6, 5.4 ],
			"to": [ 7.4, 1.95, 6.6 ],
			"faces": {
				"up" : { "texture": "#cup" },
				"down" : { "texture": "#cup" },
				"west" : { "texture": "#cup" },
				"east" : { "texture": "#cup" }
			}
		},
		{
			"name": "cup_n2_____________________________",
			"from": [ 7, 1.95, 5 ],
			"to": [ 9, 2.3, 5.2 ],
			"faces": {
				"up" : { "texture": "#cup" },
				"down" : { "texture": "#cup" },
				"north": { "texture": "#cup" },
				"south": { "texture": "#cup" },
				"west" : { "texture": "#cup" },
				"east" : { "texture": "#cup" }
			}
		},
		{
			"name": "cup_s2",
			"from": [ 7, 1.95, 6.8 ],
			"to": [ 9, 2.3, 7 ],
			"faces": {
				"up" : { "texture": "#cup" },
				"down" : { "texture": "#cup" },
				"north": { "texture": "#cup" },
				"south": { "texture": "#cup" },
				"west" : { "texture": "#cup" },
				"east" : { "texture": "#cup" }
			}
		},
		{
			"name": "cup_e2",
			"from": [ 8.8, 1.95, 5.2 ],
			"to": [ 9, 2.3, 6.8 ],
			"faces": {
				"up" : { "texture": "#cup" },
				"down" : { "texture": "#cup" },
				"west" : { "texture": "#cup" },
				"east" : { "texture": "#cup" }
			}
		},
		{
			"name": "cup_w2",
			"from": [ 7, 1.95, 5.2 ],
			"to": [ 7.2, 2.3, 6.8 ],
			"faces": {
				"up" : { "texture": "#cup" },
				"down" : { "texture": "#cup" },
				"west" : { "texture": "#cup" },
				"east" : { "texture": "#cup" }
			}
		},
		{
			"name": "cup_n3_____________________________",
			"from": [ 6.8, 2.3, 4.8 ],
			"to": [ 9.2, 2.65, 5.0 ],
			"faces": {
				"up" : { "texture": "#cup" },
				"down" : { "texture": "#cup" },
				"north": { "texture": "#cup" },
				"south": { "texture": "#cup" },
				"west" : { "texture": "#cup" },
				"east" : { "texture": "#cup" }
			}
		},
		{
			"name": "cup_s3",
			"from": [ 6.8, 2.3, 7.0 ],
			"to": [ 9.2, 2.65, 7.2 ],
			"faces": {
				"up" : { "texture": "#cup" },
				"down" : { "texture": "#cup" },
				"north": { "texture": "#cup" },
				"south": { "texture": "#cup" },
				"west" : { "texture": "#cup" },
				"east" : { "texture": "#cup" }
			}
		},
		{
			"name": "cup_e3",
			"from": [ 9.0, 2.3, 5.0 ],
			"to": [ 9.2, 2.65, 7.0 ],
			"faces": {
				"up" : { "texture": "#cup" },
				"down" : { "texture": "#cup" },
				"west" : { "texture": "#cup" },
				"east" : { "texture": "#cup" }
			}
		},
		{
			"name": "cup_w3",
			"from": [ 6.8, 2.3, 5.0 ],
			"to": [ 7.0, 2.65, 7.0 ],
			"faces": {
				"up" : { "texture": "#cup" },
				"down" : { "texture": "#cup" },
				"west" : { "texture": "#cup" },
				"east" : { "texture": "#cup" }
			}
		},
		{
			"name": "cup_n4_____________________________",
			"from": [ 6.6, 2.65, 4.6 ],
			"to": [ 9.4, 3, 4.8 ],
			"faces": {
				"up" : { "texture": "#cup" },
				"down" : { "texture": "#cup" },
				"north": { "texture": "#cup2" },
				"south": { "texture": "#cup" },
				"west" : { "texture": "#cup2" },
				"east" : { "texture": "#cup2" }
			}
		},
		{
			"name": "cup_s4",
			"from": [ 6.6, 2.65, 7.2 ],
			"to": [ 9.4, 3, 7.4 ],
			"faces": {
				"up" : { "texture": "#cup" },
				"down" : { "texture": "#cup" },
				"north": { "texture": "#cup" },
				"south": { "texture": "#cup2" },
				"west" : { "texture": "#cup2" },
				"east" : { "texture": "#cup2" }
			}
		},
		{
			"name": "cup_e4",
			"from": [ 9.2, 2.65, 4.8 ],
			"to": [ 9.4, 3, 7.2 ],
			"faces": {
				"up" : { "texture": "#cup" },
				"down" : { "texture": "#cup" },
				"west" : { "texture": "#cup" },
				"east" : { "texture": "#cup2" }
			}
		},
		{
			"name": "cup_w4",
			"from": [ 6.6, 2.65, 4.8 ],
			"to": [ 6.8, 3, 7.2 ],
			"faces": {
				"up" : { "texture": "#cup" },
				"down" : { "texture": "#cup" },
				"west" : { "texture": "#cup2" },
				"east" : { "texture": "#cup" }
			}
		},
		{
			"name": "cup_totte_____________________________",
			"from": [ 9.4, 2.65, 5.85 ],
			"to": [ 9.8, 2.95, 6.15 ],
			"faces": {
				"up" : { "texture": "#cup" },
				"down" : { "texture": "#cup" },
				"north": { "texture": "#cup" },
				"south": { "texture": "#cup" },
				"east" : { "texture": "#cup" }
			}
		},
		{
			"name": "cup_totte",
			"from": [ 9.65, 1.95, 5.85 ],
			"to": [ 9.95, 2.65, 6.15 ],
			"faces": {
				"up" : { "texture": "#cup" },
				"down" : { "texture": "#cup" },
				"north": { "texture": "#cup" },
				"south": { "texture": "#cup" },
				"west" : { "texture": "#cup" },
				"east" : { "texture": "#cup" }
			}
		},
		{
			"name": "cup_totte",
			"from": [ 8.8, 1.65, 5.85 ],
			"to": [ 9.8, 1.95, 6.15 ],
			"faces": {
				"up" : { "texture": "#cup" },
				"down" : { "texture": "#cup" },
				"north": { "texture": "#cup" },
				"south": { "texture": "#cup" },
				"east" : { "texture": "#cup" }
			}
		},

    	{
			"name": "teasara_soko_n__________________________111111111111111",
			"from": [ 2.5, 1, 5.0 ],
			"to": [ 4.5, 1.2, 5.2 ],
			"faces": {
				"down" : { "texture": "#sara" },
				"north": { "texture": "#sara" },
				"south": { "texture": "#sara" },
				"west" : { "texture": "#sara" },
				"east" : { "texture": "#sara" }
			}
		},
		{
			"name": "teasara_soko_s",
			"from": [ 2.5, 1, 6.8 ],
			"to": [ 4.5, 1.2, 7.0 ],
			"faces": {
				"down" : { "texture": "#sara" },
				"north": { "texture": "#sara" },
				"south": { "texture": "#sara" },
				"west" : { "texture": "#sara" },
				"east" : { "texture": "#sara" }
			}
		},
		{
			"name": "teasara_soko_w",
			"from": [ 2.5, 1, 5.2 ],
			"to": [ 2.7, 1.2, 6.8 ],
			"faces": {
				"down" : { "texture": "#sara" },
				"north": { "texture": "#sara" },
				"south": { "texture": "#sara" },
				"west" : { "texture": "#sara" },
				"east" : { "texture": "#sara" }
			}
		},
		{
			"name": "teasara_soko_e",
			"from": [ 4.3, 1, 5.2 ],
			"to": [ 4.5, 1.2, 6.8 ],
			"faces": {
				"down" : { "texture": "#sara" },
				"north": { "texture": "#sara" },
				"south": { "texture": "#sara" },
				"west" : { "texture": "#sara" },
				"east" : { "texture": "#sara" }
			}
		},

		{
            "name": "teasara",
            "from": [ 2.1, 1.2, 4.6 ],
            "to": [ 4.9, 1.4, 7.4 ],
            "faces": {
                "up" : { "texture": "#sara" },
                "down" : { "texture": "#sara" }
            }
        },
		{
            "name": "teasara_n___________________________",
            "from": [ 1.8, 1.2, 4.3 ],
            "to": [ 5.2, 1.4, 4.6 ],
            "faces": {
                "up" : { "texture": "#cup2" },
                "down" : { "texture": "#cup2" }
            }
        },
		{
            "name": "teasara_s",
            "from": [ 1.8, 1.2, 7.4 ],
            "to": [ 5.2, 1.4, 7.7 ],
            "faces": {
                "up" : { "texture": "#cup2" },
                "down" : { "texture": "#cup2" }
            }
        },
 		{
            "name": "teasara_e",
            "from": [ 1.8, 1.2, 4.6 ],
            "to": [ 2.1, 1.4, 7.4 ],
            "faces": {
                "up" : { "texture": "#cup2" },
                "down" : { "texture": "#cup2" }
            }
        },
		{
            "name": "teasara_w",
            "from": [ 4.9, 1.2, 4.6 ],
            "to": [ 5.2, 1.4, 7.4 ],
            "faces": {
                "up" : { "texture": "#cup2" },
                "down" : { "texture": "#cup2" }
            }
        },
		{
            "name": "teasara_n2___________________________",
            "from": [ 1.5, 1.2, 4.0 ],
            "to": [ 5.5, 1.4, 4.3 ],
            "faces": {
                "up" : { "texture": "#sara" },
                "down" : { "texture": "#sara" },
                "north": { "texture": "#sara" },
                "west" : { "texture": "#sara" },
				"east" : { "texture": "#sara" }
            }
        },
		{
            "name": "teasara_s2",
            "from": [ 1.5, 1.2, 7.7 ],
            "to": [ 5.5, 1.4, 8.0 ],
            "faces": {
                "up" : { "texture": "#sara" },
                "down" : { "texture": "#sara" },
                "south": { "texture": "#sara" },
                "west" : { "texture": "#sara" },
				"east" : { "texture": "#sara" }
            }
        },
 		{
            "name": "teasara_e2",
            "from": [ 1.5, 1.2, 4.3 ],
            "to": [ 1.8, 1.4, 7.7 ],
            "faces": {
                "up" : { "texture": "#sara" },
                "down" : { "texture": "#sara" },
                "west" : { "texture": "#sara" }
            }
        },
		{
            "name": "teasara_w2",
            "from": [ 5.2, 1.2, 4.3 ],
            "to": [ 5.5, 1.4, 7.7 ],
            "faces": {
                "up" : { "texture": "#sara" },
                "down" : { "texture": "#sara" },
				"east" : { "texture": "#sara" }
            }
        },

		{
			"name": "cup_soko",
			"from": [ 2.9, 1.4, 5.4 ],
			"to": [ 4.1, 1.6, 6.6 ],
			"faces": {
				"up" : { "texture": "#cup" },
				"down" : { "texture": "#cup" },
				"north": { "texture": "#cup" },
				"south": { "texture": "#cup" },
				"west" : { "texture": "#cup" },
				"east" : { "texture": "#cup" }
			}
		},
		{
			"name": "cup_n1_____________________________",
			"from": [ 2.7, 1.6, 5.2 ],
			"to": [ 4.3, 1.95, 5.4 ],
			"faces": {
				"up" : { "texture": "#cup" },
				"down" : { "texture": "#cup" },
				"north": { "texture": "#cup" },
				"south": { "texture": "#cup" },
				"west" : { "texture": "#cup" },
				"east" : { "texture": "#cup" }
			}
		},
		{
			"name": "cup_s1",
			"from": [ 2.7, 1.6, 6.6 ],
			"to": [ 4.3, 1.95, 6.8 ],
			"faces": {
				"up" : { "texture": "#cup" },
				"down" : { "texture": "#cup" },
				"north": { "texture": "#cup" },
				"south": { "texture": "#cup" },
				"west" : { "texture": "#cup" },
				"east" : { "texture": "#cup" }
			}
		},
		{
			"name": "cup_e1",
			"from": [ 4.1, 1.6, 5.4 ],
			"to": [ 4.3, 1.95, 6.6 ],
			"faces": {
				"up" : { "texture": "#cup" },
				"down" : { "texture": "#cup" },
				"west" : { "texture": "#cup" },
				"east" : { "texture": "#cup" }
			}
		},
		{
			"name": "cup_w1",
			"from": [ 2.7, 1.6, 5.4 ],
			"to": [ 2.9, 1.95, 6.6 ],
			"faces": {
				"up" : { "texture": "#cup" },
				"down" : { "texture": "#cup" },
				"west" : { "texture": "#cup" },
				"east" : { "texture": "#cup" }
			}
		},
		{
			"name": "cup_n2_____________________________",
			"from": [ 2.5, 1.95, 5 ],
			"to": [ 4.5, 2.3, 5.2 ],
			"faces": {
				"up" : { "texture": "#cup" },
				"down" : { "texture": "#cup" },
				"north": { "texture": "#cup" },
				"south": { "texture": "#cup" },
				"west" : { "texture": "#cup" },
				"east" : { "texture": "#cup" }
			}
		},
		{
			"name": "cup_s2",
			"from": [ 2.5, 1.95, 6.8 ],
			"to": [ 4.5, 2.3, 7 ],
			"faces": {
				"up" : { "texture": "#cup" },
				"down" : { "texture": "#cup" },
				"north": { "texture": "#cup" },
				"south": { "texture": "#cup" },
				"west" : { "texture": "#cup" },
				"east" : { "texture": "#cup" }
			}
		},
		{
			"name": "cup_e2",
			"from": [ 4.3, 1.95, 5.2 ],
			"to": [ 4.5, 2.3, 6.8 ],
			"faces": {
				"up" : { "texture": "#cup" },
				"down" : { "texture": "#cup" },
				"west" : { "texture": "#cup" },
				"east" : { "texture": "#cup" }
			}
		},
		{
			"name": "cup_w2",
			"from": [ 2.5, 1.95, 5.2 ],
			"to": [ 2.7, 2.3, 6.8 ],
			"faces": {
				"up" : { "texture": "#cup" },
				"down" : { "texture": "#cup" },
				"west" : { "texture": "#cup" },
				"east" : { "texture": "#cup" }
			}
		},
		{
			"name": "cup_n3_____________________________",
			"from": [ 2.3, 2.3, 4.8 ],
			"to": [ 4.7, 2.65, 5.0 ],
			"faces": {
				"up" : { "texture": "#cup" },
				"down" : { "texture": "#cup" },
				"north": { "texture": "#cup" },
				"south": { "texture": "#cup" },
				"west" : { "texture": "#cup" },
				"east" : { "texture": "#cup" }
			}
		},
		{
			"name": "cup_s3",
			"from": [ 2.3, 2.3, 7.0 ],
			"to": [ 4.7, 2.65, 7.2 ],
			"faces": {
				"up" : { "texture": "#cup" },
				"down" : { "texture": "#cup" },
				"north": { "texture": "#cup" },
				"south": { "texture": "#cup" },
				"west" : { "texture": "#cup" },
				"east" : { "texture": "#cup" }
			}
		},
		{
			"name": "cup_e3",
			"from": [ 4.5, 2.3, 5.0 ],
			"to": [ 4.7, 2.65, 7.0 ],
			"faces": {
				"up" : { "texture": "#cup" },
				"down" : { "texture": "#cup" },
				"west" : { "texture": "#cup" },
				"east" : { "texture": "#cup" }
			}
		},
		{
			"name": "cup_w3",
			"from": [ 2.3, 2.3, 5.0 ],
			"to": [ 2.5, 2.65, 7.0 ],
			"faces": {
				"up" : { "texture": "#cup" },
				"down" : { "texture": "#cup" },
				"west" : { "texture": "#cup" },
				"east" : { "texture": "#cup" }
			}
		},
		{
			"name": "cup_n4_____________________________",
			"from": [ 2.1, 2.65, 4.6 ],
			"to": [ 4.9, 3, 4.8 ],
			"faces": {
				"up" : { "texture": "#cup" },
				"down" : { "texture": "#cup" },
				"north": { "texture": "#cup2" },
				"south": { "texture": "#cup" },
				"west" : { "texture": "#cup2" },
				"east" : { "texture": "#cup2" }
			}
		},
		{
			"name": "cup_s4",
			"from": [ 2.1, 2.65, 7.2 ],
			"to": [ 4.9, 3, 7.4 ],
			"faces": {
				"up" : { "texture": "#cup" },
				"down" : { "texture": "#cup" },
				"north": { "texture": "#cup" },
				"south": { "texture": "#cup2" },
				"west" : { "texture": "#cup2" },
				"east" : { "texture": "#cup2" }
			}
		},
		{
			"name": "cup_e4",
			"from": [ 4.7, 2.65, 4.8 ],
			"to": [ 4.9, 3, 7.2 ],
			"faces": {
				"up" : { "texture": "#cup" },
				"down" : { "texture": "#cup" },
				"west" : { "texture": "#cup" },
				"east" : { "texture": "#cup2" }
			}
		},
		{
			"name": "cup_w4",
			"from": [ 2.1, 2.65, 4.8 ],
			"to": [ 2.3, 3, 7.2 ],
			"faces": {
				"up" : { "texture": "#cup" },
				"down" : { "texture": "#cup" },
				"west" : { "texture": "#cup2" },
				"east" : { "texture": "#cup" }
			}
		},
		{
			"name": "cup_totte_____________________________",
			"from": [ 4.9, 2.65, 5.85 ],
			"to": [ 5.3, 2.95, 6.15 ],
			"faces": {
				"up" : { "texture": "#cup" },
				"down" : { "texture": "#cup" },
				"north": { "texture": "#cup" },
				"south": { "texture": "#cup" },
				"east" : { "texture": "#cup" }
			}
		},
		{
			"name": "cup_totte",
			"from": [ 5.15, 1.95, 5.85 ],
			"to": [ 5.45, 2.65, 6.15 ],
			"faces": {
				"up" : { "texture": "#cup" },
				"down" : { "texture": "#cup" },
				"north": { "texture": "#cup" },
				"south": { "texture": "#cup" },
				"west" : { "texture": "#cup" },
				"east" : { "texture": "#cup" }
			}
		},
		{
			"name": "cup_totte",
			"from": [ 4.3, 1.65, 5.85 ],
			"to": [ 5.3, 1.95, 6.15 ],
			"faces": {
				"up" : { "texture": "#cup" },
				"down" : { "texture": "#cup" },
				"north": { "texture": "#cup" },
				"south": { "texture": "#cup" },
				"east" : { "texture": "#cup" }
			}
		},

		{
			"name": "top___________________________________________tana",
			"from": [ 0, 15.0, 0 ],
			"to": [ 16, 16.0, 10 ],
			"faces": {
				"up" : { "texture": "#side" },
				"down" : { "texture": "#side" },
				"north": { "texture": "#side" },
				"south": { "texture": "#side" },
	 			"west" : { "texture": "#side" },
				"east" : { "texture": "#side" }
			}
		},
		{
			"name": "tana_naka",
			"from": [ 1, 8.5, 1 ],
			"to": [ 15, 9, 10 ],
			"faces": {
				"up" : { "texture": "#side" },
				"down" : { "texture": "#side" },
				"south": { "texture": "#side" }
			}
		},
		{
			"name": "tana_naka",
			"from": [ 1, 4.5, 1 ],
			"to": [ 15, 5, 10 ],
			"faces": {
				"up" : { "texture": "#side" },
				"down" : { "texture": "#side" },
				"south": { "texture": "#side" }
			}
		},
		{
			"name": "tana_shita",
			"from": [ 0, 0, 0 ],
			"to": [ 16, 1, 10 ],
			"faces": {
				"up" : { "texture": "#side" },
				"down" : { "texture": "#side" },
				"north": { "texture": "#side" },
				"south": { "texture": "#side" },
	 			"west" : { "texture": "#side" },
				"east" : { "texture": "#side" }
			}
		},
		{
			"name": "kita",
			"from": [ 0, 1.0, 0 ],
			"to": [ 16, 15.0, 1 ],
			"faces": {
				"north": { "texture": "#side" },
				"south": { "texture": "#side" },
	 			"west" : { "texture": "#side" },
				"east" : { "texture": "#side" }
			}
		},
		{
			"name": "nishi",
			"from": [ 15, 1.0, 1 ],
			"to": [ 16, 15.0, 10 ],
			"faces": {
				"north": { "texture": "#side" },
				"south": { "texture": "#side" },
	 			"west" : { "texture": "#side" },
				"east" : { "texture": "#side" }
			}
		},
		{
			"name": "higashi",
			"from": [ 0, 1.0, 1 ],
			"to": [ 1, 15.0, 10 ],
			"faces": {
				"north": { "texture": "#side" },
				"south": { "texture": "#side" },
	 			"west" : { "texture": "#side" },
				"east" : { "texture": "#side" }
			}
		}
	]
}
