{
    "parent": "chinjufumod:block/block_mkasa_pink_open",
    "display": {
        "gui": {
            "rotation": [ 30, 45, 0 ],
            "translation": [ 0, -1.5, 0 ],
            "scale": [ 0.65, 0.65, 0.65 ]
        },
        "thirdperson_righthand": {
            "rotation": [ 70, 0, 0 ],
            "translation": [ 0, 4, 14 ],
            "scale": [ 1.45, 1.45, 1.45 ]
        },
        "firstperson_righthand": {
            "rotation": [ 0, 0, 0 ],
            "translation": [ -2, 9, 7 ],
            "scale": [ 1.45, 1.45, 1.45 ]
        }
    }
}
